parameter_sweep/__init__.py
parameter_sweep/_compat.py
parameter_sweep/conftest.py
parameter_sweep/differential.py
parameter_sweep/functions.py
parameter_sweep/model_manager.py
parameter_sweep/parallel_utils.py
parameter_sweep/parameter_sweep.py
parameter_sweep/reader.py
parameter_sweep/sampling_types.py
parameter_sweep/writer.py
parameter_sweep/loop_tool/__init__.py
parameter_sweep/loop_tool/data_merging_tool.py
parameter_sweep/loop_tool/loop_tool.py
parameter_sweep/loop_tool/tests/ro_setup.py
parameter_sweep/loop_tool/tests/test_all_options.yaml
parameter_sweep/loop_tool/tests/test_bad_default.yaml
parameter_sweep/loop_tool/tests/test_data_merging_tool.py
parameter_sweep/loop_tool/tests/test_diff.yaml
parameter_sweep/loop_tool/tests/test_expected_diff_directory.yaml
parameter_sweep/loop_tool/tests/test_expected_option_directory.yaml
parameter_sweep/loop_tool/tests/test_expected_sweep_directory.yaml
parameter_sweep/loop_tool/tests/test_loop_tool.py
parameter_sweep/loop_tool/tests/test_missing_sweep_loop.yaml
parameter_sweep/loop_tool/tests/test_sweep.yaml
parameter_sweep/parallel/__init__.py
parameter_sweep/parallel/concurrent_futures_parallel_manager.py
parameter_sweep/parallel/mpi_parallel_manager.py
parameter_sweep/parallel/multiprocessing_parallel_manager.py
parameter_sweep/parallel/parallel_manager.py
parameter_sweep/parallel/parallel_manager_factory.py
parameter_sweep/parallel/ray_io_parallel_manager.py
parameter_sweep/parallel/results.py
parameter_sweep/parallel/single_process_parallel_manager.py
parameter_sweep/parallel/MPI/__init__.py
parameter_sweep/parallel/MPI/dummy_mpi.py
parameter_sweep/parallel/MPI/tests/__init__.py
parameter_sweep/parallel/MPI/tests/test_dummy_mpi.py
parameter_sweep/parallel/tests/__init__.py
parameter_sweep/parallel/tests/test_concurrent_futures_parallel_manager.py
parameter_sweep/parallel/tests/test_multiprocessing_parallel_manager.py
parameter_sweep/parallel/tests/test_parallel_manager.py
parameter_sweep-0.1.0.dist-info/LICENSE.md
parameter_sweep-0.1.0.dist-info/METADATA
parameter_sweep-0.1.0.dist-info/WHEEL
parameter_sweep-0.1.0.dist-info/top_level.txt
parameter_sweep-0.1.0.dist-info/RECORD
