Metadata-Version: 2.1
Name: parameter-sweep
Version: 0.1.0
License-File: LICENSE.md
Requires-Dist: pyomo>=6.7.3
Requires-Dist: numpy
Requires-Dist: h5py
Requires-Dist: pyyaml
Requires-Dist: idaes-pse
Provides-Extra: ray
Requires-Dist: ray; extra == "ray"
Provides-Extra: mpi
Requires-Dist: mpi4py; extra == "mpi"
Provides-Extra: testing
Requires-Dist: pytest>=8; extra == "testing"
Requires-Dist: idaes-pse; extra == "testing"
Requires-Dist: watertap; extra == "testing"
Requires-Dist: requests; extra == "testing"
